[
  {
    "Open":106076.1,
    "High":106256.9,
    "Low":106076.1,
    "Close":106252.1,
    "Volume":58.47,
    "level_low":104302.5,
    "level_center":104749.74,
    "level_high":105725.06,
    "volume_24h":542653390.2999999523,
    "price_change_24h":1.33,
    "price_change_4h":1.62,
    "price_change_1h":1.43,
    "max_price_change_24h_pc":2.23,
    "ATR":156.6,
    "ATR_pc":0.15,
    "BB_ma":105226.7,
    "BB_upper":106262.82,
    "BB_lower":104190.58,
    "BB_signal":1,
    "fast_ma":105876.92,
    "slow_ma":104982.65,
    "signal_ma_cross":1,
    "fast_der_sm_norm":1.39,
    "signal_volume":1,
    "signal_level":5.0,
    "signal_level_change":0.0,
    "symbol":"BTCUSDT",
    "index":"2025-06-20T08:10:00.000Z"
  },
  {
    "Open":2562.39,
    "High":2567.0,
    "Low":2561.59,
    "Close":2565.6,
    "Volume":853.32,
    "level_low":2502.89,
    "level_center":2521.65,
    "level_high":2545.37,
    "volume_24h":222152440.5099999905,
    "price_change_24h":1.59,
    "price_change_4h":1.85,
    "price_change_1h":1.57,
    "max_price_change_24h_pc":3.25,
    "ATR":6.61,
    "ATR_pc":0.26,
    "BB_ma":2535.57,
    "BB_upper":2564.81,
    "BB_lower":2506.32,
    "BB_signal":2,
    "fast_ma":2553.36,
    "slow_ma":2528.38,
    "signal_ma_cross":1,
    "fast_der_sm_norm":1.95,
    "signal_volume":1,
    "signal_level":5.0,
    "signal_level_change":0.0,
    "symbol":"ETHUSDT",
    "index":"2025-06-20T08:10:00.000Z"
  },
  {
    "Open":2.17,
    "High":2.17,
    "Low":2.17,
    "Close":2.17,
    "Volume":194389.43,
    "level_low":2.15,
    "level_center":2.16,
    "level_high":2.17,
    "volume_24h":46296321.8400000036,
    "price_change_24h":0.63,
    "price_change_4h":0.86,
    "price_change_1h":1.36,
    "max_price_change_24h_pc":1.73,
    "ATR":0.0,
    "ATR_pc":0.22,
    "BB_ma":2.16,
    "BB_upper":2.18,
    "BB_lower":2.14,
    "BB_signal":1,
    "fast_ma":2.17,
    "slow_ma":2.15,
    "signal_ma_cross":1,
    "fast_der_sm_norm":1.08,
    "signal_volume":1,
    "signal_level":5.0,
    "signal_level_change":1.0,
    "symbol":"XRPUSDT",
    "index":"2025-06-20T08:10:00.000Z"
  },
  {
    "Open":147.88,
    "High":148.08,
    "Low":147.78,
    "Close":147.98,
    "Volume":2960.51,
    "level_low":143.82,
    "level_center":145.47,
    "level_high":147.21,
    "volume_24h":90296063.0199999958,
    "price_change_24h":1.75,
    "price_change_4h":1.82,
    "price_change_1h":1.63,
    "max_price_change_24h_pc":3.65,
    "ATR":0.41,
    "ATR_pc":0.28,
    "BB_ma":146.42,
    "BB_upper":148.25,
    "BB_lower":144.59,
    "BB_signal":1,
    "fast_ma":147.53,
    "slow_ma":145.98,
    "signal_ma_cross":1,
    "fast_der_sm_norm":1.44,
    "signal_volume":0,
    "signal_level":5.0,
    "signal_level_change":0.0,
    "symbol":"SOLUSDT",
    "index":"2025-06-20T08:10:00.000Z"
  },
  {
    "Open":0.63,
    "High":0.63,
    "Low":0.62,
    "Close":0.62,
    "Volume":508516.36,
    "level_low":0.62,
    "level_center":0.63,
    "level_high":0.63,
    "volume_24h":92878829.049999997,
    "price_change_24h":1.91,
    "price_change_4h":-0.62,
    "price_change_1h":-0.43,
    "max_price_change_24h_pc":4.74,
    "ATR":0.0,
    "ATR_pc":0.37,
    "BB_ma":0.63,
    "BB_upper":0.63,
    "BB_lower":0.62,
    "BB_signal":-2,
    "fast_ma":0.63,
    "slow_ma":0.63,
    "signal_ma_cross":0,
    "fast_der_sm_norm":-0.42,
    "signal_volume":0,
    "signal_level":-1.0,
    "signal_level_change":-1.0,
    "symbol":"MNTUSDT",
    "index":"2025-06-20T08:10:00.000Z"
  },
  {
    "Open":0.17,
    "High":0.17,
    "Low":0.17,
    "Close":0.17,
    "Volume":465045.0,
    "level_low":0.17,
    "level_center":0.17,
    "level_high":0.17,
    "volume_24h":13491824.4700000007,
    "price_change_24h":0.55,
    "price_change_4h":1.22,
    "price_change_1h":1.77,
    "max_price_change_24h_pc":2.72,
    "ATR":0.0,
    "ATR_pc":0.31,
    "BB_ma":0.17,
    "BB_upper":0.17,
    "BB_lower":0.17,
    "BB_signal":1,
    "fast_ma":0.17,
    "slow_ma":0.17,
    "signal_ma_cross":1,
    "fast_der_sm_norm":1.52,
    "signal_volume":0,
    "signal_level":5.0,
    "signal_level_change":0.0,
    "symbol":"DOGEUSDT",
    "index":"2025-06-20T08:10:00.000Z"
  },
  {
    "Open":9.38,
    "High":9.4,
    "Low":9.38,
    "Close":9.4,
    "Volume":13847.17,
    "level_low":9.0,
    "level_center":9.2,
    "level_high":9.33,
    "volume_24h":12148463.3800000008,
    "price_change_24h":0.48,
    "price_change_4h":1.16,
    "price_change_1h":1.59,
    "max_price_change_24h_pc":5.6,
    "ATR":0.03,
    "ATR_pc":0.3,
    "BB_ma":9.3,
    "BB_upper":9.41,
    "BB_lower":9.19,
    "BB_signal":1,
    "fast_ma":9.36,
    "slow_ma":9.26,
    "signal_ma_cross":1,
    "fast_der_sm_norm":1.32,
    "signal_volume":0,
    "signal_level":5.0,
    "signal_level_change":0.0,
    "symbol":"TRUMPUSDT",
    "index":"2025-06-20T08:10:00.000Z"
  },
  {
    "Open":0.0,
    "High":0.0,
    "Low":0.0,
    "Close":0.0,
    "Volume":172434660118.0,
    "level_low":0.0,
    "level_center":0.0,
    "level_high":0.0,
    "volume_24h":16043284.7799999993,
    "price_change_24h":0.93,
    "price_change_4h":3.16,
    "price_change_1h":2.6,
    "max_price_change_24h_pc":4.16,
    "ATR":0.0,
    "ATR_pc":0.46,
    "BB_ma":0.0,
    "BB_upper":0.0,
    "BB_lower":0.0,
    "BB_signal":2,
    "fast_ma":0.0,
    "slow_ma":0.0,
    "signal_ma_cross":1,
    "fast_der_sm_norm":1.88,
    "signal_volume":1,
    "signal_level":5.0,
    "signal_level_change":0.0,
    "symbol":"PEPEUSDT",
    "index":"2025-06-20T08:10:00.000Z"
  },
  {
    "Open":0.06,
    "High":0.06,
    "Low":0.06,
    "Close":0.06,
    "Volume":0.0,
    "level_low":0.06,
    "level_center":0.06,
    "level_high":0.06,
    "volume_24h":67992.33,
    "price_change_24h":-0.77,
    "price_change_4h":0.24,
    "price_change_1h":0.49,
    "max_price_change_24h_pc":2.39,
    "ATR":0.0,
    "ATR_pc":0.08,
    "BB_ma":0.06,
    "BB_upper":0.06,
    "BB_lower":0.06,
    "BB_signal":1,
    "fast_ma":0.06,
    "slow_ma":0.06,
    "signal_ma_cross":1,
    "fast_der_sm_norm":-0.1,
    "signal_volume":0,
    "signal_level":1.0,
    "signal_level_change":0.0,
    "symbol":"MILKUSDT",
    "index":"2025-06-20T08:10:00.000Z"
  },
  {
    "Open":2.86,
    "High":2.87,
    "Low":2.86,
    "Close":2.87,
    "Volume":33354.86,
    "level_low":2.79,
    "level_center":2.81,
    "level_high":2.84,
    "volume_24h":16298003.5500000007,
    "price_change_24h":2.21,
    "price_change_4h":2.52,
    "price_change_1h":2.99,
    "max_price_change_24h_pc":3.62,
    "ATR":0.01,
    "ATR_pc":0.47,
    "BB_ma":2.82,
    "BB_upper":2.88,
    "BB_lower":2.76,
    "BB_signal":1,
    "fast_ma":2.85,
    "slow_ma":2.81,
    "signal_ma_cross":1,
    "fast_der_sm_norm":2.38,
    "signal_volume":0,
    "signal_level":5.0,
    "signal_level_change":0.0,
    "symbol":"SUIUSDT",
    "index":"2025-06-20T08:10:00.000Z"
  },
  {
    "Open":0.82,
    "High":0.82,
    "Low":0.82,
    "Close":0.82,
    "Volume":78083.79,
    "level_low":0.78,
    "level_center":0.79,
    "level_high":0.81,
    "volume_24h":10797522.4499999993,
    "price_change_24h":2.6,
    "price_change_4h":3.73,
    "price_change_1h":3.56,
    "max_price_change_24h_pc":5.81,
    "ATR":0.01,
    "ATR_pc":0.64,
    "BB_ma":0.8,
    "BB_upper":0.82,
    "BB_lower":0.78,
    "BB_signal":1,
    "fast_ma":0.81,
    "slow_ma":0.79,
    "signal_ma_cross":1,
    "fast_der_sm_norm":2.97,
    "signal_volume":0,
    "signal_level":5.0,
    "signal_level_change":0.0,
    "symbol":"WIFUSDT",
    "index":"2025-06-20T08:10:00.000Z"
  },
  {
    "Open":0.6,
    "High":0.61,
    "Low":0.6,
    "Close":0.61,
    "Volume":93329.33,
    "level_low":0.59,
    "level_center":0.6,
    "level_high":0.6,
    "volume_24h":9902774.4399999995,
    "price_change_24h":0.98,
    "price_change_4h":1.37,
    "price_change_1h":2.16,
    "max_price_change_24h_pc":3.2,
    "ATR":0.0,
    "ATR_pc":0.35,
    "BB_ma":0.6,
    "BB_upper":0.61,
    "BB_lower":0.59,
    "BB_signal":1,
    "fast_ma":0.6,
    "slow_ma":0.6,
    "signal_ma_cross":1,
    "fast_der_sm_norm":1.87,
    "signal_volume":0,
    "signal_level":5.0,
    "signal_level_change":0.0,
    "symbol":"ADAUSDT",
    "index":"2025-06-20T08:10:00.000Z"
  },
  {
    "Open":1.75,
    "High":1.77,
    "Low":1.75,
    "Close":1.77,
    "Volume":39850.75,
    "level_low":1.66,
    "level_center":1.68,
    "level_high":1.73,
    "volume_24h":7827698.8300000001,
    "price_change_24h":4.45,
    "price_change_4h":6.97,
    "price_change_1h":5.8,
    "max_price_change_24h_pc":7.8,
    "ATR":0.01,
    "ATR_pc":0.83,
    "BB_ma":1.7,
    "BB_upper":1.78,
    "BB_lower":1.63,
    "BB_signal":1,
    "fast_ma":1.74,
    "slow_ma":1.68,
    "signal_ma_cross":1,
    "fast_der_sm_norm":4.11,
    "signal_volume":0,
    "signal_level":5.0,
    "signal_level_change":0.0,
    "symbol":"VIRTUALUSDT",
    "index":"2025-06-20T08:10:00.000Z"
  },
  {
    "Open":0.29,
    "High":0.29,
    "Low":0.29,
    "Close":0.29,
    "Volume":169155.1,
    "level_low":0.28,
    "level_center":0.29,
    "level_high":0.29,
    "volume_24h":6321670.8600000003,
    "price_change_24h":2.06,
    "price_change_4h":3.4,
    "price_change_1h":2.71,
    "max_price_change_24h_pc":4.76,
    "ATR":0.0,
    "ATR_pc":0.49,
    "BB_ma":0.29,
    "BB_upper":0.29,
    "BB_lower":0.28,
    "BB_signal":1,
    "fast_ma":0.29,
    "slow_ma":0.29,
    "signal_ma_cross":1,
    "fast_der_sm_norm":2.16,
    "signal_volume":1,
    "signal_level":5.0,
    "signal_level_change":0.0,
    "symbol":"ENAUSDT",
    "index":"2025-06-20T08:10:00.000Z"
  },
  {
    "Open":0.13,
    "High":0.13,
    "Low":0.13,
    "Close":0.13,
    "Volume":31798.0,
    "level_low":0.12,
    "level_center":0.13,
    "level_high":0.13,
    "volume_24h":1512202.72,
    "price_change_24h":3.73,
    "price_change_4h":2.4,
    "price_change_1h":2.55,
    "max_price_change_24h_pc":6.0,
    "ATR":0.0,
    "ATR_pc":0.57,
    "BB_ma":0.13,
    "BB_upper":0.13,
    "BB_lower":0.12,
    "BB_signal":2,
    "fast_ma":0.13,
    "slow_ma":0.12,
    "signal_ma_cross":1,
    "fast_der_sm_norm":3.27,
    "signal_volume":0,
    "signal_level":5.0,
    "signal_level_change":0.0,
    "symbol":"HAEDALUSDT",
    "index":"2025-06-20T08:10:00.000Z"
  },
  {
    "Open":0.3,
    "High":0.3,
    "Low":0.3,
    "Close":0.3,
    "Volume":180712.64,
    "level_low":0.29,
    "level_center":0.29,
    "level_high":0.3,
    "volume_24h":5930451.9000000004,
    "price_change_24h":-0.53,
    "price_change_4h":4.08,
    "price_change_1h":3.43,
    "max_price_change_24h_pc":7.25,
    "ATR":0.0,
    "ATR_pc":0.73,
    "BB_ma":0.29,
    "BB_upper":0.3,
    "BB_lower":0.28,
    "BB_signal":1,
    "fast_ma":0.3,
    "slow_ma":0.29,
    "signal_ma_cross":1,
    "fast_der_sm_norm":1.84,
    "signal_volume":1,
    "signal_level":5.0,
    "signal_level_change":0.0,
    "symbol":"POPCATUSDT",
    "index":"2025-06-20T08:10:00.000Z"
  },
  {
    "Open":0.78,
    "High":0.78,
    "Low":0.78,
    "Close":0.78,
    "Volume":31185.19,
    "level_low":0.76,
    "level_center":0.77,
    "level_high":0.78,
    "volume_24h":6510299.5099999998,
    "price_change_24h":-0.28,
    "price_change_4h":2.04,
    "price_change_1h":2.66,
    "max_price_change_24h_pc":4.66,
    "ATR":0.0,
    "ATR_pc":0.44,
    "BB_ma":0.77,
    "BB_upper":0.78,
    "BB_lower":0.75,
    "BB_signal":1,
    "fast_ma":0.78,
    "slow_ma":0.76,
    "signal_ma_cross":1,
    "fast_der_sm_norm":2.1,
    "signal_volume":0,
    "signal_level":3.0,
    "signal_level_change":1.0,
    "symbol":"ONDOUSDT",
    "index":"2025-06-20T08:10:00.000Z"
  },
  {
    "Open":0.07,
    "High":0.07,
    "Low":0.07,
    "Close":0.07,
    "Volume":148198.71,
    "level_low":0.07,
    "level_center":0.07,
    "level_high":0.07,
    "volume_24h":2356081.2799999998,
    "price_change_24h":0.95,
    "price_change_4h":3.05,
    "price_change_1h":1.85,
    "max_price_change_24h_pc":4.13,
    "ATR":0.0,
    "ATR_pc":0.41,
    "BB_ma":0.07,
    "BB_upper":0.07,
    "BB_lower":0.07,
    "BB_signal":1,
    "fast_ma":0.07,
    "slow_ma":0.07,
    "signal_ma_cross":1,
    "fast_der_sm_norm":1.57,
    "signal_volume":0,
    "signal_level":5.0,
    "signal_level_change":0.0,
    "symbol":"KASUSDT",
    "index":"2025-06-20T08:10:00.000Z"
  },
  {
    "Open":0.15,
    "High":0.15,
    "Low":0.15,
    "Close":0.15,
    "Volume":477178.65,
    "level_low":0.15,
    "level_center":0.15,
    "level_high":0.15,
    "volume_24h":3566039.8399999999,
    "price_change_24h":1.06,
    "price_change_4h":1.57,
    "price_change_1h":1.48,
    "max_price_change_24h_pc":3.04,
    "ATR":0.0,
    "ATR_pc":0.26,
    "BB_ma":0.15,
    "BB_upper":0.15,
    "BB_lower":0.15,
    "BB_signal":1,
    "fast_ma":0.15,
    "slow_ma":0.15,
    "signal_ma_cross":1,
    "fast_der_sm_norm":1.41,
    "signal_volume":1,
    "signal_level":5.0,
    "signal_level_change":0.0,
    "symbol":"HBARUSDT",
    "index":"2025-06-20T08:10:00.000Z"
  },
  {
    "Open":0.27,
    "High":0.27,
    "Low":0.27,
    "Close":0.27,
    "Volume":234463.83,
    "level_low":0.27,
    "level_center":0.27,
    "level_high":0.28,
    "volume_24h":11717791.1600000001,
    "price_change_24h":-1.09,
    "price_change_4h":-0.76,
    "price_change_1h":0.04,
    "max_price_change_24h_pc":1.49,
    "ATR":0.0,
    "ATR_pc":0.13,
    "BB_ma":0.27,
    "BB_upper":0.27,
    "BB_lower":0.27,
    "BB_signal":0,
    "fast_ma":0.27,
    "slow_ma":0.27,
    "signal_ma_cross":0,
    "fast_der_sm_norm":0.48,
    "signal_volume":1,
    "signal_level":-5.0,
    "signal_level_change":0.0,
    "symbol":"TRXUSDT",
    "index":"2025-06-20T08:10:00.000Z"
  },
  {
    "Open":85.69,
    "High":85.81,
    "Low":85.69,
    "Close":85.77,
    "Volume":441.6,
    "level_low":84.62,
    "level_center":85.04,
    "level_high":85.47,
    "volume_24h":8149017.1299999999,
    "price_change_24h":0.8,
    "price_change_4h":0.82,
    "price_change_1h":1.32,
    "max_price_change_24h_pc":2.14,
    "ATR":0.19,
    "ATR_pc":0.22,
    "BB_ma":85.01,
    "BB_upper":85.91,
    "BB_lower":84.11,
    "BB_signal":1,
    "fast_ma":85.54,
    "slow_ma":84.87,
    "signal_ma_cross":1,
    "fast_der_sm_norm":1.18,
    "signal_volume":1,
    "signal_level":5.0,
    "signal_level_change":0.0,
    "symbol":"LTCUSDT",
    "index":"2025-06-20T08:10:00.000Z"
  },
  {
    "Open":3355.2,
    "High":3355.6,
    "Low":3354.0,
    "Close":3355.5,
    "Volume":2.34,
    "level_low":3358.06,
    "level_center":3372.38,
    "level_high":3379.01,
    "volume_24h":1739431.5900000001,
    "price_change_24h":-0.34,
    "price_change_4h":-0.24,
    "price_change_1h":-0.24,
    "max_price_change_24h_pc":1.02,
    "ATR":2.36,
    "ATR_pc":0.07,
    "BB_ma":3357.02,
    "BB_upper":3363.85,
    "BB_lower":3350.18,
    "BB_signal":-1,
    "fast_ma":3355.8,
    "slow_ma":3356.96,
    "signal_ma_cross":0,
    "fast_der_sm_norm":-0.16,
    "signal_volume":0,
    "signal_level":-5.0,
    "signal_level_change":0.0,
    "symbol":"XAUTUSDT",
    "index":"2025-06-20T08:10:00.000Z"
  },
  {
    "Open":0.24,
    "High":0.24,
    "Low":0.24,
    "Close":0.24,
    "Volume":71239.1,
    "level_low":0.22,
    "level_center":0.23,
    "level_high":0.24,
    "volume_24h":1412540.3700000001,
    "price_change_24h":7.25,
    "price_change_4h":8.65,
    "price_change_1h":5.39,
    "max_price_change_24h_pc":11.49,
    "ATR":0.0,
    "ATR_pc":0.88,
    "BB_ma":0.23,
    "BB_upper":0.24,
    "BB_lower":0.22,
    "BB_signal":1,
    "fast_ma":0.24,
    "slow_ma":0.23,
    "signal_ma_cross":1,
    "fast_der_sm_norm":5.36,
    "signal_volume":0,
    "signal_level":5.0,
    "signal_level_change":0.0,
    "symbol":"PNUTUSDT",
    "index":"2025-06-20T08:10:00.000Z"
  },
  {
    "Open":0.1,
    "High":0.1,
    "Low":0.1,
    "Close":0.1,
    "Volume":126078.0,
    "level_low":0.1,
    "level_center":0.1,
    "level_high":0.1,
    "volume_24h":1297425.6899999999,
    "price_change_24h":3.47,
    "price_change_4h":4.54,
    "price_change_1h":2.32,
    "max_price_change_24h_pc":8.19,
    "ATR":0.0,
    "ATR_pc":0.82,
    "BB_ma":0.1,
    "BB_upper":0.1,
    "BB_lower":0.1,
    "BB_signal":1,
    "fast_ma":0.1,
    "slow_ma":0.1,
    "signal_ma_cross":1,
    "fast_der_sm_norm":1.09,
    "signal_volume":0,
    "signal_level":5.0,
    "signal_level_change":1.0,
    "symbol":"GOATUSDT",
    "index":"2025-06-20T08:10:00.000Z"
  },
  {
    "Open":0.5,
    "High":0.51,
    "Low":0.5,
    "Close":0.51,
    "Volume":6037.6,
    "level_low":0.49,
    "level_center":0.5,
    "level_high":0.5,
    "volume_24h":447306.92,
    "price_change_24h":-0.36,
    "price_change_4h":2.77,
    "price_change_1h":2.68,
    "max_price_change_24h_pc":5.65,
    "ATR":0.0,
    "ATR_pc":0.56,
    "BB_ma":0.5,
    "BB_upper":0.51,
    "BB_lower":0.49,
    "BB_signal":1,
    "fast_ma":0.5,
    "slow_ma":0.49,
    "signal_ma_cross":1,
    "fast_der_sm_norm":0.65,
    "signal_volume":0,
    "signal_level":5.0,
    "signal_level_change":1.0,
    "symbol":"INITUSDT",
    "index":"2025-06-20T08:10:00.000Z"
  },
  {
    "Open":0.18,
    "High":0.18,
    "Low":0.18,
    "Close":0.18,
    "Volume":106818.64,
    "level_low":0.17,
    "level_center":0.18,
    "level_high":0.18,
    "volume_24h":2554938.9700000002,
    "price_change_24h":-0.17,
    "price_change_4h":0.63,
    "price_change_1h":0.8,
    "max_price_change_24h_pc":5.98,
    "ATR":0.0,
    "ATR_pc":0.4,
    "BB_ma":0.18,
    "BB_upper":0.18,
    "BB_lower":0.17,
    "BB_signal":3,
    "fast_ma":0.18,
    "slow_ma":0.18,
    "signal_ma_cross":1,
    "fast_der_sm_norm":1.53,
    "signal_volume":1,
    "signal_level":4.0,
    "signal_level_change":2.0,
    "symbol":"APEXUSDT",
    "index":"2025-06-20T08:10:00.000Z"
  },
  {
    "Open":13.23,
    "High":13.27,
    "Low":13.23,
    "Close":13.26,
    "Volume":5507.75,
    "level_low":12.98,
    "level_center":13.09,
    "level_high":13.23,
    "volume_24h":10111570.1999999993,
    "price_change_24h":0.71,
    "price_change_4h":2.06,
    "price_change_1h":2.19,
    "max_price_change_24h_pc":3.72,
    "ATR":0.04,
    "ATR_pc":0.32,
    "BB_ma":13.07,
    "BB_upper":13.28,
    "BB_lower":12.87,
    "BB_signal":1,
    "fast_ma":13.19,
    "slow_ma":13.03,
    "signal_ma_cross":1,
    "fast_der_sm_norm":1.91,
    "signal_volume":0,
    "signal_level":4.0,
    "signal_level_change":0.0,
    "symbol":"LINKUSDT",
    "index":"2025-06-20T08:10:00.000Z"
  },
  {
    "Open":0.0,
    "High":0.0,
    "Low":0.0,
    "Close":0.0,
    "Volume":99545.75,
    "level_low":0.0,
    "level_center":0.0,
    "level_high":0.0,
    "volume_24h":419107.44,
    "price_change_24h":0.46,
    "price_change_4h":3.64,
    "price_change_1h":2.97,
    "max_price_change_24h_pc":6.24,
    "ATR":0.0,
    "ATR_pc":0.57,
    "BB_ma":0.0,
    "BB_upper":0.0,
    "BB_lower":0.0,
    "BB_signal":1,
    "fast_ma":0.0,
    "slow_ma":0.0,
    "signal_ma_cross":1,
    "fast_der_sm_norm":1.76,
    "signal_volume":0,
    "signal_level":5.0,
    "signal_level_change":0.0,
    "symbol":"DEGENUSDT",
    "index":"2025-06-20T08:10:00.000Z"
  },
  {
    "Open":2720.47,
    "High":2742.1,
    "Low":2714.57,
    "Close":2721.12,
    "Volume":0.81,
    "level_low":2679.21,
    "level_center":2698.01,
    "level_high":2732.19,
    "volume_24h":321633.85,
    "price_change_24h":1.45,
    "price_change_4h":1.31,
    "price_change_1h":0.91,
    "max_price_change_24h_pc":5.16,
    "ATR":25.43,
    "ATR_pc":0.93,
    "BB_ma":2695.65,
    "BB_upper":2723.03,
    "BB_lower":2668.27,
    "BB_signal":2,
    "fast_ma":2709.63,
    "slow_ma":2687.37,
    "signal_ma_cross":1,
    "fast_der_sm_norm":1.65,
    "signal_volume":0,
    "signal_level":2.0,
    "signal_level_change":0.0,
    "symbol":"CMETHUSDT",
    "index":"2025-06-20T08:10:00.000Z"
  },
  {
    "Open":0.0,
    "High":0.0,
    "Low":0.0,
    "Close":0.0,
    "Volume":780998796.0,
    "level_low":0.0,
    "level_center":0.0,
    "level_high":0.0,
    "volume_24h":1280011.22,
    "price_change_24h":2.32,
    "price_change_4h":2.6,
    "price_change_1h":2.6,
    "max_price_change_24h_pc":4.84,
    "ATR":0.0,
    "ATR_pc":0.43,
    "BB_ma":0.0,
    "BB_upper":0.0,
    "BB_lower":0.0,
    "BB_signal":1,
    "fast_ma":0.0,
    "slow_ma":0.0,
    "signal_ma_cross":1,
    "fast_der_sm_norm":2.13,
    "signal_volume":0,
    "signal_level":5.0,
    "signal_level_change":0.0,
    "symbol":"BONKUSDT",
    "index":"2025-06-20T08:10:00.000Z"
  },
  {
    "Open":0.17,
    "High":0.17,
    "Low":0.17,
    "Close":0.17,
    "Volume":167070.57,
    "level_low":0.16,
    "level_center":0.16,
    "level_high":0.17,
    "volume_24h":4117755.9900000002,
    "price_change_24h":-2.0,
    "price_change_4h":3.41,
    "price_change_1h":3.15,
    "max_price_change_24h_pc":8.0,
    "ATR":0.0,
    "ATR_pc":0.72,
    "BB_ma":0.16,
    "BB_upper":0.17,
    "BB_lower":0.16,
    "BB_signal":1,
    "fast_ma":0.17,
    "slow_ma":0.16,
    "signal_ma_cross":1,
    "fast_der_sm_norm":0.9,
    "signal_volume":0,
    "signal_level":3.0,
    "signal_level_change":0.0,
    "symbol":"AI16ZUSDT",
    "index":"2025-06-20T08:10:00.000Z"
  },
  {
    "Open":0.31,
    "High":0.31,
    "Low":0.31,
    "Close":0.31,
    "Volume":150766.99,
    "level_low":0.3,
    "level_center":0.3,
    "level_high":0.31,
    "volume_24h":5222167.7400000002,
    "price_change_24h":0.81,
    "price_change_4h":3.44,
    "price_change_1h":2.86,
    "max_price_change_24h_pc":4.52,
    "ATR":0.0,
    "ATR_pc":0.44,
    "BB_ma":0.3,
    "BB_upper":0.31,
    "BB_lower":0.3,
    "BB_signal":1,
    "fast_ma":0.31,
    "slow_ma":0.3,
    "signal_ma_cross":1,
    "fast_der_sm_norm":2.39,
    "signal_volume":1,
    "signal_level":5.0,
    "signal_level_change":0.0,
    "symbol":"ARBUSDT",
    "index":"2025-06-20T08:10:00.000Z"
  },
  {
    "Open":0.25,
    "High":0.25,
    "Low":0.25,
    "Close":0.25,
    "Volume":41528.2,
    "level_low":0.25,
    "level_center":0.25,
    "level_high":0.25,
    "volume_24h":1106042.04,
    "price_change_24h":-0.12,
    "price_change_4h":0.88,
    "price_change_1h":1.13,
    "max_price_change_24h_pc":2.4,
    "ATR":0.0,
    "ATR_pc":0.23,
    "BB_ma":0.25,
    "BB_upper":0.25,
    "BB_lower":0.25,
    "BB_signal":1,
    "fast_ma":0.25,
    "slow_ma":0.25,
    "signal_ma_cross":1,
    "fast_der_sm_norm":0.92,
    "signal_volume":1,
    "signal_level":2.0,
    "signal_level_change":0.0,
    "symbol":"XLMUSDT",
    "index":"2025-06-20T08:10:00.000Z"
  },
  {
    "Open":0.01,
    "High":0.01,
    "Low":0.01,
    "Close":0.01,
    "Volume":655043.0,
    "level_low":0.01,
    "level_center":0.01,
    "level_high":0.01,
    "volume_24h":906514.5600000001,
    "price_change_24h":0.08,
    "price_change_4h":3.16,
    "price_change_1h":2.25,
    "max_price_change_24h_pc":6.83,
    "ATR":0.0,
    "ATR_pc":0.81,
    "BB_ma":0.01,
    "BB_upper":0.01,
    "BB_lower":0.01,
    "BB_signal":1,
    "fast_ma":0.01,
    "slow_ma":0.01,
    "signal_ma_cross":1,
    "fast_der_sm_norm":1.86,
    "signal_volume":0,
    "signal_level":5.0,
    "signal_level_change":0.0,
    "symbol":"EPTUSDT",
    "index":"2025-06-20T08:10:00.000Z"
  },
  {
    "Open":2.98,
    "High":2.98,
    "Low":2.98,
    "Close":2.98,
    "Volume":8469.1,
    "level_low":2.92,
    "level_center":2.95,
    "level_high":2.97,
    "volume_24h":6798316.5700000003,
    "price_change_24h":1.81,
    "price_change_4h":0.85,
    "price_change_1h":0.78,
    "max_price_change_24h_pc":2.61,
    "ATR":0.01,
    "ATR_pc":0.21,
    "BB_ma":2.96,
    "BB_upper":2.98,
    "BB_lower":2.94,
    "BB_signal":1,
    "fast_ma":2.98,
    "slow_ma":2.96,
    "signal_ma_cross":1,
    "fast_der_sm_norm":0.67,
    "signal_volume":0,
    "signal_level":5.0,
    "signal_level_change":0.0,
    "symbol":"TONUSDT",
    "index":"2025-06-20T08:10:00.000Z"
  },
  {
    "Open":648.8,
    "High":649.2,
    "Low":648.8,
    "Close":649.2,
    "Volume":45.67,
    "level_low":639.99,
    "level_center":642.29,
    "level_high":645.04,
    "volume_24h":3528774.6899999999,
    "price_change_24h":0.57,
    "price_change_4h":0.89,
    "price_change_1h":0.57,
    "max_price_change_24h_pc":1.72,
    "ATR":0.56,
    "ATR_pc":0.09,
    "BB_ma":646.35,
    "BB_upper":649.08,
    "BB_lower":643.62,
    "BB_signal":2,
    "fast_ma":648.0,
    "slow_ma":645.53,
    "signal_ma_cross":1,
    "fast_der_sm_norm":0.69,
    "signal_volume":1,
    "signal_level":5.0,
    "signal_level_change":0.0,
    "symbol":"BNBUSDT",
    "index":"2025-06-20T08:10:00.000Z"
  },
  {
    "Open":18.35,
    "High":18.38,
    "Low":18.34,
    "Close":18.38,
    "Volume":801.02,
    "level_low":17.76,
    "level_center":17.99,
    "level_high":18.3,
    "volume_24h":8853434.6899999995,
    "price_change_24h":2.22,
    "price_change_4h":2.22,
    "price_change_1h":1.78,
    "max_price_change_24h_pc":4.33,
    "ATR":0.07,
    "ATR_pc":0.37,
    "BB_ma":18.19,
    "BB_upper":18.49,
    "BB_lower":17.88,
    "BB_signal":1,
    "fast_ma":18.33,
    "slow_ma":18.1,
    "signal_ma_cross":1,
    "fast_der_sm_norm":0.33,
    "signal_volume":0,
    "signal_level":5.0,
    "signal_level_change":0.0,
    "symbol":"AVAXUSDT",
    "index":"2025-06-20T08:10:00.000Z"
  },
  {
    "Open":0.0,
    "High":0.0,
    "Low":0.0,
    "Close":0.0,
    "Volume":1969166862.4000000954,
    "level_low":0.0,
    "level_center":0.0,
    "level_high":0.0,
    "volume_24h":3643441.8399999999,
    "price_change_24h":1.2,
    "price_change_4h":1.77,
    "price_change_1h":1.33,
    "max_price_change_24h_pc":2.68,
    "ATR":0.0,
    "ATR_pc":0.21,
    "BB_ma":0.0,
    "BB_upper":0.0,
    "BB_lower":0.0,
    "BB_signal":1,
    "fast_ma":0.0,
    "slow_ma":0.0,
    "signal_ma_cross":1,
    "fast_der_sm_norm":1.36,
    "signal_volume":0,
    "signal_level":5.0,
    "signal_level_change":0.0,
    "symbol":"SHIBUSDT",
    "index":"2025-06-20T08:10:00.000Z"
  },
  {
    "Open":0.34,
    "High":0.34,
    "Low":0.34,
    "Close":0.34,
    "Volume":5484.0,
    "level_low":0.33,
    "level_center":0.35,
    "level_high":0.37,
    "volume_24h":2329132.2799999998,
    "price_change_24h":-1.35,
    "price_change_4h":1.32,
    "price_change_1h":1.78,
    "max_price_change_24h_pc":16.36,
    "ATR":0.0,
    "ATR_pc":0.42,
    "BB_ma":0.33,
    "BB_upper":0.34,
    "BB_lower":0.33,
    "BB_signal":1,
    "fast_ma":0.34,
    "slow_ma":0.33,
    "signal_ma_cross":1,
    "fast_der_sm_norm":2.14,
    "signal_volume":0,
    "signal_level":-3.0,
    "signal_level_change":0.0,
    "symbol":"WCTUSDT",
    "index":"2025-06-20T08:10:00.000Z"
  },
  {
    "Open":0.44,
    "High":0.44,
    "Low":0.44,
    "Close":0.44,
    "Volume":4791.4,
    "level_low":0.43,
    "level_center":0.43,
    "level_high":0.44,
    "volume_24h":1046206.54,
    "price_change_24h":1.26,
    "price_change_4h":1.52,
    "price_change_1h":2.73,
    "max_price_change_24h_pc":3.25,
    "ATR":0.0,
    "ATR_pc":0.41,
    "BB_ma":0.43,
    "BB_upper":0.44,
    "BB_lower":0.43,
    "BB_signal":1,
    "fast_ma":0.44,
    "slow_ma":0.43,
    "signal_ma_cross":1,
    "fast_der_sm_norm":2.27,
    "signal_volume":0,
    "signal_level":5.0,
    "signal_level_change":0.0,
    "symbol":"WALUSDT",
    "index":"2025-06-20T08:10:00.000Z"
  },
  {
    "Open":0.0,
    "High":0.0,
    "Low":0.0,
    "Close":0.0,
    "Volume":9771055.0,
    "level_low":0.0,
    "level_center":0.0,
    "level_high":0.0,
    "volume_24h":934722.04,
    "price_change_24h":-4.49,
    "price_change_4h":2.94,
    "price_change_1h":2.52,
    "max_price_change_24h_pc":9.37,
    "ATR":0.0,
    "ATR_pc":0.39,
    "BB_ma":0.0,
    "BB_upper":0.0,
    "BB_lower":0.0,
    "BB_signal":1,
    "fast_ma":0.0,
    "slow_ma":0.0,
    "signal_ma_cross":1,
    "fast_der_sm_norm":2.38,
    "signal_volume":1,
    "signal_level":-1.0,
    "signal_level_change":0.0,
    "symbol":"TOSHIUSDT",
    "index":"2025-06-20T08:10:00.000Z"
  },
  {
    "Open":0.32,
    "High":0.32,
    "Low":0.32,
    "Close":0.32,
    "Volume":7289.57,
    "level_low":0.32,
    "level_center":0.32,
    "level_high":0.32,
    "volume_24h":2236710.7599999998,
    "price_change_24h":-0.06,
    "price_change_4h":2.01,
    "price_change_1h":1.63,
    "max_price_change_24h_pc":3.76,
    "ATR":0.0,
    "ATR_pc":0.33,
    "BB_ma":0.32,
    "BB_upper":0.33,
    "BB_lower":0.32,
    "BB_signal":1,
    "fast_ma":0.32,
    "slow_ma":0.32,
    "signal_ma_cross":1,
    "fast_der_sm_norm":1.45,
    "signal_volume":0,
    "signal_level":5.0,
    "signal_level_change":0.0,
    "symbol":"SUSDT",
    "index":"2025-06-20T08:10:00.000Z"
  },
  {
    "Open":0.01,
    "High":0.01,
    "Low":0.01,
    "Close":0.01,
    "Volume":1492688.0,
    "level_low":0.01,
    "level_center":0.01,
    "level_high":0.01,
    "volume_24h":1649392.4399999999,
    "price_change_24h":2.87,
    "price_change_4h":4.31,
    "price_change_1h":2.76,
    "max_price_change_24h_pc":6.28,
    "ATR":0.0,
    "ATR_pc":0.46,
    "BB_ma":0.01,
    "BB_upper":0.01,
    "BB_lower":0.01,
    "BB_signal":1,
    "fast_ma":0.01,
    "slow_ma":0.01,
    "signal_ma_cross":1,
    "fast_der_sm_norm":2.48,
    "signal_volume":1,
    "signal_level":5.0,
    "signal_level_change":0.0,
    "symbol":"PENGUUSDT",
    "index":"2025-06-20T08:10:00.000Z"
  },
  {
    "Open":3.54,
    "High":3.55,
    "Low":3.54,
    "Close":3.55,
    "Volume":11540.33,
    "level_low":3.49,
    "level_center":3.53,
    "level_high":3.56,
    "volume_24h":3994227.0800000001,
    "price_change_24h":-0.81,
    "price_change_4h":1.2,
    "price_change_1h":1.98,
    "max_price_change_24h_pc":3.85,
    "ATR":0.01,
    "ATR_pc":0.32,
    "BB_ma":3.51,
    "BB_upper":3.56,
    "BB_lower":3.45,
    "BB_signal":1,
    "fast_ma":3.54,
    "slow_ma":3.5,
    "signal_ma_cross":1,
    "fast_der_sm_norm":1.49,
    "signal_volume":1,
    "signal_level":2.0,
    "signal_level_change":0.0,
    "symbol":"DOTUSDT",
    "index":"2025-06-20T08:10:00.000Z"
  },
  {
    "Open":2.19,
    "High":2.2,
    "Low":2.19,
    "Close":2.2,
    "Volume":16819.0,
    "level_low":2.14,
    "level_center":2.16,
    "level_high":2.19,
    "volume_24h":4782462.9699999997,
    "price_change_24h":0.55,
    "price_change_4h":2.71,
    "price_change_1h":2.42,
    "max_price_change_24h_pc":4.07,
    "ATR":0.01,
    "ATR_pc":0.39,
    "BB_ma":2.16,
    "BB_upper":2.2,
    "BB_lower":2.12,
    "BB_signal":1,
    "fast_ma":2.18,
    "slow_ma":2.15,
    "signal_ma_cross":1,
    "fast_der_sm_norm":2.18,
    "signal_volume":1,
    "signal_level":5.0,
    "signal_level_change":1.0,
    "symbol":"NEARUSDT",
    "index":"2025-06-20T08:10:00.000Z"
  }
]